aiecs/__init__.py
aiecs/__main__.py
aiecs/aiecs_client.py
aiecs/main.py
aiecs/application/__init__.py
aiecs/application/executors/__init__.py
aiecs/application/executors/operation_executor.py
aiecs/application/knowledge_graph/__init__.py
aiecs/application/knowledge_graph/builder/__init__.py
aiecs/application/knowledge_graph/builder/data_quality.py
aiecs/application/knowledge_graph/builder/data_reshaping.py
aiecs/application/knowledge_graph/builder/document_builder.py
aiecs/application/knowledge_graph/builder/graph_builder.py
aiecs/application/knowledge_graph/builder/import_optimizer.py
aiecs/application/knowledge_graph/builder/schema_inference.py
aiecs/application/knowledge_graph/builder/schema_mapping.py
aiecs/application/knowledge_graph/builder/structured_pipeline.py
aiecs/application/knowledge_graph/builder/text_chunker.py
aiecs/application/knowledge_graph/extractors/__init__.py
aiecs/application/knowledge_graph/extractors/base.py
aiecs/application/knowledge_graph/extractors/llm_entity_extractor.py
aiecs/application/knowledge_graph/extractors/llm_relation_extractor.py
aiecs/application/knowledge_graph/extractors/ner_entity_extractor.py
aiecs/application/knowledge_graph/fusion/__init__.py
aiecs/application/knowledge_graph/fusion/ab_testing.py
aiecs/application/knowledge_graph/fusion/abbreviation_expander.py
aiecs/application/knowledge_graph/fusion/alias_index.py
aiecs/application/knowledge_graph/fusion/alias_matcher.py
aiecs/application/knowledge_graph/fusion/cache_coordinator.py
aiecs/application/knowledge_graph/fusion/entity_deduplicator.py
aiecs/application/knowledge_graph/fusion/entity_linker.py
aiecs/application/knowledge_graph/fusion/evaluation_dataset.py
aiecs/application/knowledge_graph/fusion/knowledge_fusion.py
aiecs/application/knowledge_graph/fusion/matching_config.py
aiecs/application/knowledge_graph/fusion/name_normalizer.py
aiecs/application/knowledge_graph/fusion/relation_deduplicator.py
aiecs-1.9.6.dist-info/licenses/LICENSE
aiecs-1.9.6.dist-info/METADATA
aiecs-1.9.6.dist-info/WHEEL
aiecs-1.9.6.dist-info/entry_points.txt
aiecs-1.9.6.dist-info/top_level.txt
aiecs-1.9.6.dist-info/RECORD
