Metadata-Version: 2.4
Name: aiecs
Version: 1.9.6
Summary: AI Execute Services - A middleware framework for AI-powered task execution and tool orchestration
Author-email: AIECS Team <iretbl@gmail.com>
License-Expression: MIT
Project-URL: Homepage, https://github.com/Howmany-Zeta/AI-Execute-Services
Project-URL: Bug Tracker, https://github.com/Howmany-Zeta/AI-Execute-Services/issues
Project-URL: Documentation, https://aiecs.readthedocs.io
Keywords: ai,middleware,llm,orchestration,async,tools
Classifier: Development Status :: 4 - Beta
Classifier: Intended Audience :: Developers
Classifier: Topic :: Software Development :: Libraries :: Python Modules
Classifier: Programming Language :: Python :: 3
Classifier: Programming Language :: Python :: 3.10
Classifier: Programming Language :: Python :: 3.11
Classifier: Programming Language :: Python :: 3.12
Classifier: Framework :: FastAPI
Classifier: Framework :: Celery
Classifier: Topic :: Scientific/Engineering :: Artificial Intelligence
Requires-Python: <3.13,>=3.11
License-File: LICENSE
Requires-Dist: fastapi<0.116.0,>=0.115.12
Requires-Dist: httpx<0.29.0,>=0.28.1
Requires-Dist: requests<3.0.0,>=2.32.3
Requires-Dist: uvicorn[standard]<0.35.0,>=0.34.2
Requires-Dist: python-dotenv<2.0.0,>=1.1.0
Requires-Dist: pydantic<3.0.0,>=2.11.5
Requires-Dist: pydantic-settings<3.0.0,>=2.9.1
Requires-Dist: cachetools<6.0.0,>=5.0.0
Requires-Dist: typing-extensions<5.0.0,>=4.13.2
Requires-Dist: aiofiles<25.0.0,>=24.1.0
Requires-Dist: celery<6.0.0,>=5.5.2
Requires-Dist: redis<7.0.0,>=6.2.0
Requires-Dist: python-socketio<6.0.0,>=5.13.0
Requires-Dist: python-engineio<5.0.0,>=4.12.1
Requires-Dist: tenacity<10.0.0,>=9.1.2
Requires-Dist: flower<3.0.0,>=2.0.1
Requires-Dist: openai<1.76.0,>=1.68.2
Requires-Dist: google-cloud-aiplatform<2.0.0,>=1.80.0
Requires-Dist: google-genai<2.0.0,>=1.0.0
Requires-Dist: google-api-python-client<3.0.0,>=2.108.0
Requires-Dist: google-auth<3.0.0,>=2.25.0
Requires-Dist: google-auth-httplib2<1.0.0,>=0.2.0
Requires-Dist: google-auth-oauthlib<2.0.0,>=1.2.0
Requires-Dist: langchain<0.4.0,>=0.3.26
Requires-Dist: langgraph<0.6.0,>=0.5.3
Requires-Dist: weasel==0.4.1
Requires-Dist: spacy<4.0.0,>=3.8.7
Requires-Dist: rake-nltk<2.0.0,>=1.0.6
Requires-Dist: numpy<3.0.0,>=2.4.1
Requires-Dist: pandas<3.0.0,>=2.2.3
Requires-Dist: scipy<2.0.0,>=1.15.3
Requires-Dist: scikit-learn<2.0.0,>=1.5.0
Requires-Dist: statsmodels<0.15.0,>=0.14.4
Requires-Dist: pyreadstat<2.0.0,>=1.2.9
Requires-Dist: pyarrow<22.0.0,>=21.0.0
Requires-Dist: tabulate<0.10.0,>=0.9.0
Requires-Dist: python-docx<2.0.0,>=1.1.2
Requires-Dist: python-pptx<2.0.0,>=1.0.2
Requires-Dist: openpyxl<4.0.0,>=3.1.5
Requires-Dist: pdfplumber<0.12.0,>=0.11.7
Requires-Dist: pdfminer-six==20250506
Requires-Dist: tika<4.0.0,>=3.1.0
Requires-Dist: matplotlib<4.0.0,>=3.10.3
Requires-Dist: seaborn<0.14.0,>=0.13.2
Requires-Dist: jinja2<4.0.0,>=3.1.6
Requires-Dist: beautifulsoup4<5.0.0,>=4.13.4
Requires-Dist: lxml<6.0.0,>=5.4.0
Requires-Dist: playwright<2.0.0,>=1.52.0
Requires-Dist: playwright-stealth<2.0.0,>=1.0.6
Requires-Dist: curl_cffi<1.0.0,>=0.7.0
Requires-Dist: pytesseract<0.4.0,>=0.3.13
Requires-Dist: pillow<12.0.0,>=11.2.1
Requires-Dist: scrapy<3.0.0,>=2.13.3
Requires-Dist: pyyaml<7.0.0,>=6.0.2
Requires-Dist: markdown<4.0,>=3.8
Requires-Dist: bleach<7.0.0,>=6.2.0
Requires-Dist: python-frontmatter<2.0.0,>=1.1.0
Requires-Dist: sqlalchemy<3.0.0,>=2.0.41
Requires-Dist: asyncpg<1.0.0,>=0.30.0
Requires-Dist: aiosqlite<1.0.0,>=0.20.0
Requires-Dist: networkx<4.0.0,>=3.0
Requires-Dist: lark-parser<0.13.0,>=0.12.0
Requires-Dist: prometheus-client<1.0.0,>=0.21.1
Requires-Dist: jaeger-client<5.0.0,>=4.8.0
Requires-Dist: opentracing<3.0.0,>=2.4.0
Requires-Dist: psutil<8.0.0,>=7.0.0
Provides-Extra: dev
Requires-Dist: pytest<9.0.0,>=8.4.2; extra == "dev"
Requires-Dist: pytest-asyncio<2.0.0,>=1.2.0; extra == "dev"
Requires-Dist: pytest-cov<8.0.0,>=7.0.0; extra == "dev"
Requires-Dist: pytest-timeout<3.0.0,>=2.4.0; extra == "dev"
Requires-Dist: mypy<2.0.0,>=1.18.2; extra == "dev"
Requires-Dist: flake8<8.0.0,>=7.3.0; extra == "dev"
Requires-Dist: black<26.0.0,>=25.1.0; extra == "dev"
Requires-Dist: types-aiofiles>=25.1.0.20251011; extra == "dev"
Requires-Dist: types-cachetools>=6.2.0.20251022; extra == "dev"
Requires-Dist: types-colorama>=0.4.15.20250801; extra == "dev"
Requires-Dist: types-tqdm>=4.67.0.20250809; extra == "dev"
Requires-Dist: types-pyyaml>=6.0.12.20250915; extra == "dev"
Requires-Dist: types-opentracing>=2.4.10.20250622; extra == "dev"
Requires-Dist: types-lxml>=2025.8.25; extra == "dev"
Requires-Dist: types-bleach>=6.3.0.20251115; extra == "dev"
Provides-Extra: docs
Requires-Dist: sphinx<8.0.0,>=7.0.0; extra == "docs"
Requires-Dist: sphinx-rtd-theme<3.0.0,>=2.0.0; extra == "docs"
Requires-Dist: sphinx-autodoc-typehints<3.0.0,>=2.0.0; extra == "docs"
Requires-Dist: myst-parser<3.0.0,>=2.0.0; extra == "docs"
Requires-Dist: sphinx-copybutton<1.0.0,>=0.5.0; extra == "docs"
Dynamic: license-file
